twitch_thumbnail/__init__.py
twitch_thumbnail/asynchronous.py
twitch_thumbnail/exceptions.py
twitch_thumbnail/ffmpeg.py
twitch_thumbnail/streamlink.py
twitch_thumbnail/synchronous.py
twitch_thumbnail-1.1.1.dist-info/METADATA
twitch_thumbnail-1.1.1.dist-info/WHEEL
twitch_thumbnail-1.1.1.dist-info/top_level.txt
twitch_thumbnail-1.1.1.dist-info/RECORD
